{
  "timestamp": "2025-06-04T23:31:07.339675",
  "components": {
    "Market Data Pipeline": "Partial",
    "AI Family Communication": "Ready",
    "Trading Engine": "Partial",
    "Paper Trading": "Partial",
    "System Monitor": "Ready",
    "Training System": "Ready"
  },
  "ai_family": {
    "status": "Operational",
    "claudae": "Learning Phase",
    "nyala": "Ready for Trading",
    "deon": "Risk Assessment Ready"
  },
  "recent_changes": [
    "Market data pipeline implemented",
    "AI family communication established",
    "Training system activated",
    "System monitoring configured"
  ],
  "next_priorities": [
    "Complete market data pipeline",
    "Integrate NYALA trading engine"
  ]
}